chromadb/__init__.py
chromadb/app.py
chromadb/config.py
chromadb/errors.py
chromadb/log_config.yml
chromadb/py.typed
chromadb/types.py
chromadb/api/__init__.py
chromadb/api/async_api.py
chromadb/api/async_client.py
chromadb/api/async_fastapi.py
chromadb/api/base_http_client.py
chromadb/api/client.py
chromadb/api/fastapi.py
chromadb/api/segment.py
chromadb/api/shared_system_client.py
chromadb/api/types.py
chromadb/api/models/AsyncCollection.py
chromadb/api/models/Collection.py
chromadb/api/models/CollectionCommon.py
chromadb/auth/__init__.py
chromadb/auth/basic_authn/__init__.py
chromadb/auth/simple_rbac_authz/__init__.py
chromadb/auth/token_authn/__init__.py
chromadb/cli/__init__.py
chromadb/cli/cli.py
chromadb/cli/utils.py
chromadb/db/__init__.py
chromadb/db/base.py
chromadb/db/migrations.py
chromadb/db/system.py
chromadb/db/impl/__init__.py
chromadb/db/impl/sqlite.py
chromadb/db/impl/sqlite_pool.py
chromadb/db/impl/grpc/client.py
chromadb/db/impl/grpc/server.py
chromadb/db/mixins/embeddings_queue.py
chromadb/db/mixins/sysdb.py
chromadb/experimental/density_relevance.ipynb
chromadb/ingest/__init__.py
chromadb/ingest/impl/utils.py
chromadb/logservice/logservice.py
chromadb/migrations/__init__.py
chromadb/migrations/embeddings_queue/00001-embeddings.sqlite.sql
chromadb/migrations/metadb/00001-embedding-metadata.sqlite.sql
chromadb/migrations/metadb/00002-embedding-metadata.sqlite.sql
chromadb/migrations/metadb/00003-full-text-tokenize.sqlite.sql
chromadb/migrations/sysdb/00001-collections.sqlite.sql
chromadb/migrations/sysdb/00002-segments.sqlite.sql
chromadb/migrations/sysdb/00003-collection-dimension.sqlite.sql
chromadb/migrations/sysdb/00004-tenants-databases.sqlite.sql
chromadb/migrations/sysdb/00005-remove-topic.sqlite.sql
chromadb/migrations/sysdb/00006-collection-segment-metadata.sqlite.sql
chromadb/proto/__init__.py
chromadb/proto/chroma_pb2.py
chromadb/proto/chroma_pb2.pyi
chromadb/proto/chroma_pb2_grpc.py
chromadb/proto/convert.py
chromadb_pysqlite3-0.5.3.dist-info/LICENSE
chromadb_pysqlite3-0.5.3.dist-info/METADATA
chromadb_pysqlite3-0.5.3.dist-info/WHEEL
chromadb_pysqlite3-0.5.3.dist-info/entry_points.txt
chromadb_pysqlite3-0.5.3.dist-info/top_level.txt
chromadb_pysqlite3-0.5.3.dist-info/RECORD
